{
  "updated": "2026-04-23T17:58:07.996179+00:00",
  "ranges": {
    "1W": [
      {
        "ticker": "PAR",
        "company": "PAR",
        "change_pct": -6.06,
        "price": 13.32
      },
      {
        "ticker": "TOST",
        "company": "Toast",
        "change_pct": -5.12,
        "price": 27.59
      },
      {
        "ticker": "DASH",
        "company": "DoorDash",
        "change_pct": -5.19,
        "price": 174.34
      },
      {
        "ticker": "VYX",
        "company": "NCR Voyix",
        "change_pct": -3.94,
        "price": 6.59
      },
      {
        "ticker": "LSPD",
        "company": "Lightspeed",
        "change_pct": -3.3,
        "price": 9.37
      },
      {
        "ticker": "FOUR",
        "company": "Shift4",
        "change_pct": -7.47,
        "price": 45.95
      },
      {
        "ticker": "XYZ",
        "company": "Block (Square)",
        "change_pct": -2.95,
        "price": 69.15
      },
      {
        "ticker": "GPN",
        "company": "Global Payments",
        "change_pct": -6.66,
        "price": 67.55
      },
      {
        "ticker": "FISV",
        "company": "Fiserv",
        "change_pct": -4.74,
        "price": 60.94
      },
      {
        "ticker": "UBER",
        "company": "Uber",
        "change_pct": -4.09,
        "price": 73.96
      }
    ],
    "1M": [
      {
        "ticker": "PAR",
        "company": "PAR",
        "change_pct": -5.13,
        "price": 13.32
      },
      {
        "ticker": "TOST",
        "company": "Toast",
        "change_pct": 0.11,
        "price": 27.59
      },
      {
        "ticker": "DASH",
        "company": "DoorDash",
        "change_pct": 9.14,
        "price": 174.6
      },
      {
        "ticker": "VYX",
        "company": "NCR Voyix",
        "change_pct": 0.15,
        "price": 6.59
      },
      {
        "ticker": "LSPD",
        "company": "Lightspeed",
        "change_pct": 4.93,
        "price": 9.37
      },
      {
        "ticker": "FOUR",
        "company": "Shift4",
        "change_pct": 4.36,
        "price": 45.95
      },
      {
        "ticker": "XYZ",
        "company": "Block (Square)",
        "change_pct": 13.05,
        "price": 69.15
      },
      {
        "ticker": "GPN",
        "company": "Global Payments",
        "change_pct": -5.08,
        "price": 67.45
      },
      {
        "ticker": "FISV",
        "company": "Fiserv",
        "change_pct": 5.53,
        "price": 60.9
      },
      {
        "ticker": "UBER",
        "company": "Uber",
        "change_pct": -1.57,
        "price": 73.94
      }
    ],
    "3M": [
      {
        "ticker": "PAR",
        "company": "PAR",
        "change_pct": -57.78,
        "price": 13.34
      },
      {
        "ticker": "TOST",
        "company": "Toast",
        "change_pct": -18.42,
        "price": 27.58
      },
      {
        "ticker": "DASH",
        "company": "DoorDash",
        "change_pct": -15.83,
        "price": 174.43
      },
      {
        "ticker": "VYX",
        "company": "NCR Voyix",
        "change_pct": -36.99,
        "price": 6.59
      },
      {
        "ticker": "LSPD",
        "company": "Lightspeed",
        "change_pct": -18.52,
        "price": 9.37
      },
      {
        "ticker": "FOUR",
        "company": "Shift4",
        "change_pct": -30.6,
        "price": 45.95
      },
      {
        "ticker": "XYZ",
        "company": "Block (Square)",
        "change_pct": 3.48,
        "price": 69.15
      },
      {
        "ticker": "GPN",
        "company": "Global Payments",
        "change_pct": -10.02,
        "price": 67.45
      },
      {
        "ticker": "FISV",
        "company": "Fiserv",
        "change_pct": -9.86,
        "price": 60.9
      },
      {
        "ticker": "UBER",
        "company": "Uber",
        "change_pct": -10.17,
        "price": 73.93
      }
    ],
    "YTD": [
      {
        "ticker": "PAR",
        "company": "PAR",
        "change_pct": -61.62,
        "price": 13.34
      },
      {
        "ticker": "TOST",
        "company": "Toast",
        "change_pct": -24.78,
        "price": 27.58
      },
      {
        "ticker": "DASH",
        "company": "DoorDash",
        "change_pct": -24.32,
        "price": 174.46
      },
      {
        "ticker": "VYX",
        "company": "NCR Voyix",
        "change_pct": -35.94,
        "price": 6.59
      },
      {
        "ticker": "LSPD",
        "company": "Lightspeed",
        "change_pct": -22.63,
        "price": 9.37
      },
      {
        "ticker": "FOUR",
        "company": "Shift4",
        "change_pct": -29.94,
        "price": 45.95
      },
      {
        "ticker": "XYZ",
        "company": "Block (Square)",
        "change_pct": -3.27,
        "price": 69.13
      },
      {
        "ticker": "GPN",
        "company": "Global Payments",
        "change_pct": -12.68,
        "price": 67.45
      },
      {
        "ticker": "FISV",
        "company": "Fiserv",
        "change_pct": -11.37,
        "price": 60.9
      },
      {
        "ticker": "UBER",
        "company": "Uber",
        "change_pct": -14.19,
        "price": 73.96
      }
    ]
  }
}