{
  "updated": "2026-05-21T17:13:42.151721+00:00",
  "ranges": {
    "1W": [
      {
        "ticker": "PAR",
        "company": "PAR",
        "change_pct": -3.74,
        "price": 14.15
      },
      {
        "ticker": "TOST",
        "company": "Toast",
        "change_pct": 0.04,
        "price": 23.06
      },
      {
        "ticker": "DASH",
        "company": "DoorDash",
        "change_pct": 0.35,
        "price": 159.75
      },
      {
        "ticker": "VYX",
        "company": "NCR Voyix",
        "change_pct": -6.01,
        "price": 6.26
      },
      {
        "ticker": "LSPD",
        "company": "Lightspeed",
        "change_pct": -7.47,
        "price": 8.17
      },
      {
        "ticker": "FOUR",
        "company": "Shift4",
        "change_pct": 0.93,
        "price": 42.41
      },
      {
        "ticker": "XYZ",
        "company": "Block (Square)",
        "change_pct": -2.05,
        "price": 68.92
      },
      {
        "ticker": "GPN",
        "company": "Global Payments",
        "change_pct": 6.08,
        "price": 71.69
      },
      {
        "ticker": "FISV",
        "company": "Fiserv",
        "change_pct": 0.18,
        "price": 55.43
      },
      {
        "ticker": "UBER",
        "company": "Uber",
        "change_pct": -2.34,
        "price": 73.33
      }
    ],
    "1M": [
      {
        "ticker": "PAR",
        "company": "PAR",
        "change_pct": 0.86,
        "price": 14.15
      },
      {
        "ticker": "TOST",
        "company": "Toast",
        "change_pct": -19.58,
        "price": 23.06
      },
      {
        "ticker": "DASH",
        "company": "DoorDash",
        "change_pct": -12.44,
        "price": 159.75
      },
      {
        "ticker": "VYX",
        "company": "NCR Voyix",
        "change_pct": -10.95,
        "price": 6.26
      },
      {
        "ticker": "LSPD",
        "company": "Lightspeed",
        "change_pct": -16.72,
        "price": 8.17
      },
      {
        "ticker": "FOUR",
        "company": "Shift4",
        "change_pct": -12.75,
        "price": 42.41
      },
      {
        "ticker": "XYZ",
        "company": "Block (Square)",
        "change_pct": -3.97,
        "price": 68.9
      },
      {
        "ticker": "GPN",
        "company": "Global Payments",
        "change_pct": 0.14,
        "price": 71.69
      },
      {
        "ticker": "FISV",
        "company": "Fiserv",
        "change_pct": -12.42,
        "price": 55.4
      },
      {
        "ticker": "UBER",
        "company": "Uber",
        "change_pct": -5.09,
        "price": 73.33
      }
    ],
    "3M": [
      {
        "ticker": "PAR",
        "company": "PAR",
        "change_pct": -13.67,
        "price": 14.15
      },
      {
        "ticker": "TOST",
        "company": "Toast",
        "change_pct": -15.58,
        "price": 23.06
      },
      {
        "ticker": "DASH",
        "company": "DoorDash",
        "change_pct": -9.47,
        "price": 159.75
      },
      {
        "ticker": "VYX",
        "company": "NCR Voyix",
        "change_pct": -18.06,
        "price": 6.26
      },
      {
        "ticker": "LSPD",
        "company": "Lightspeed",
        "change_pct": -9.52,
        "price": 8.17
      },
      {
        "ticker": "FOUR",
        "company": "Shift4",
        "change_pct": -3.77,
        "price": 42.41
      },
      {
        "ticker": "XYZ",
        "company": "Block (Square)",
        "change_pct": 8.17,
        "price": 68.9
      },
      {
        "ticker": "GPN",
        "company": "Global Payments",
        "change_pct": -5.95,
        "price": 71.68
      },
      {
        "ticker": "FISV",
        "company": "Fiserv",
        "change_pct": -11.04,
        "price": 55.42
      },
      {
        "ticker": "UBER",
        "company": "Uber",
        "change_pct": -2.78,
        "price": 73.32
      }
    ],
    "YTD": [
      {
        "ticker": "PAR",
        "company": "PAR",
        "change_pct": -59.29,
        "price": 14.15
      },
      {
        "ticker": "TOST",
        "company": "Toast",
        "change_pct": -37.11,
        "price": 23.06
      },
      {
        "ticker": "DASH",
        "company": "DoorDash",
        "change_pct": -30.7,
        "price": 159.75
      },
      {
        "ticker": "VYX",
        "company": "NCR Voyix",
        "change_pct": -38.96,
        "price": 6.28
      },
      {
        "ticker": "LSPD",
        "company": "Lightspeed",
        "change_pct": -32.54,
        "price": 8.17
      },
      {
        "ticker": "FOUR",
        "company": "Shift4",
        "change_pct": -35.45,
        "price": 42.34
      },
      {
        "ticker": "XYZ",
        "company": "Block (Square)",
        "change_pct": -3.61,
        "price": 68.89
      },
      {
        "ticker": "GPN",
        "company": "Global Payments",
        "change_pct": -7.21,
        "price": 71.68
      },
      {
        "ticker": "FISV",
        "company": "Fiserv",
        "change_pct": -19.37,
        "price": 55.4
      },
      {
        "ticker": "UBER",
        "company": "Uber",
        "change_pct": -14.92,
        "price": 73.33
      }
    ]
  }
}