{
  "updated": "2026-05-19T17:25:24.060557+00:00",
  "ranges": {
    "1W": [
      {
        "ticker": "PAR",
        "company": "PAR",
        "change_pct": 2.68,
        "price": 14.55
      },
      {
        "ticker": "TOST",
        "company": "Toast",
        "change_pct": 1.37,
        "price": 22.64
      },
      {
        "ticker": "DASH",
        "company": "DoorDash",
        "change_pct": 4.27,
        "price": 155.43
      },
      {
        "ticker": "VYX",
        "company": "NCR Voyix",
        "change_pct": -6.35,
        "price": 6.49
      },
      {
        "ticker": "LSPD",
        "company": "Lightspeed",
        "change_pct": -2.25,
        "price": 8.68
      },
      {
        "ticker": "FOUR",
        "company": "Shift4",
        "change_pct": 1.52,
        "price": 41.49
      },
      {
        "ticker": "XYZ",
        "company": "Block (Square)",
        "change_pct": -0.23,
        "price": 69.62
      },
      {
        "ticker": "GPN",
        "company": "Global Payments",
        "change_pct": 2.01,
        "price": 68.36
      },
      {
        "ticker": "FISV",
        "company": "Fiserv",
        "change_pct": 6.91,
        "price": 55.99
      },
      {
        "ticker": "UBER",
        "company": "Uber",
        "change_pct": -0.41,
        "price": 74.4
      }
    ],
    "1M": [
      {
        "ticker": "PAR",
        "company": "PAR",
        "change_pct": -0.27,
        "price": 14.54
      },
      {
        "ticker": "TOST",
        "company": "Toast",
        "change_pct": -22.43,
        "price": 22.64
      },
      {
        "ticker": "DASH",
        "company": "DoorDash",
        "change_pct": -18.11,
        "price": 155.43
      },
      {
        "ticker": "VYX",
        "company": "NCR Voyix",
        "change_pct": -7.81,
        "price": 6.49
      },
      {
        "ticker": "LSPD",
        "company": "Lightspeed",
        "change_pct": -12.06,
        "price": 8.68
      },
      {
        "ticker": "FOUR",
        "company": "Shift4",
        "change_pct": -15.88,
        "price": 41.49
      },
      {
        "ticker": "XYZ",
        "company": "Block (Square)",
        "change_pct": -5.77,
        "price": 69.62
      },
      {
        "ticker": "GPN",
        "company": "Global Payments",
        "change_pct": -6.14,
        "price": 68.36
      },
      {
        "ticker": "FISV",
        "company": "Fiserv",
        "change_pct": -12.71,
        "price": 55.99
      },
      {
        "ticker": "UBER",
        "company": "Uber",
        "change_pct": -3.99,
        "price": 74.4
      }
    ],
    "3M": [
      {
        "ticker": "PAR",
        "company": "PAR",
        "change_pct": -33.52,
        "price": 14.54
      },
      {
        "ticker": "TOST",
        "company": "Toast",
        "change_pct": -16.38,
        "price": 22.64
      },
      {
        "ticker": "DASH",
        "company": "DoorDash",
        "change_pct": -11.83,
        "price": 155.43
      },
      {
        "ticker": "VYX",
        "company": "NCR Voyix",
        "change_pct": -32.4,
        "price": 6.49
      },
      {
        "ticker": "LSPD",
        "company": "Lightspeed",
        "change_pct": -7.17,
        "price": 8.68
      },
      {
        "ticker": "FOUR",
        "company": "Shift4",
        "change_pct": -29.06,
        "price": 41.49
      },
      {
        "ticker": "XYZ",
        "company": "Block (Square)",
        "change_pct": 30.82,
        "price": 69.62
      },
      {
        "ticker": "GPN",
        "company": "Global Payments",
        "change_pct": -16.84,
        "price": 68.36
      },
      {
        "ticker": "FISV",
        "company": "Fiserv",
        "change_pct": -8.88,
        "price": 56.01
      },
      {
        "ticker": "UBER",
        "company": "Uber",
        "change_pct": 0.7,
        "price": 74.38
      }
    ],
    "YTD": [
      {
        "ticker": "PAR",
        "company": "PAR",
        "change_pct": -58.17,
        "price": 14.54
      },
      {
        "ticker": "TOST",
        "company": "Toast",
        "change_pct": -38.26,
        "price": 22.64
      },
      {
        "ticker": "DASH",
        "company": "DoorDash",
        "change_pct": -32.57,
        "price": 155.43
      },
      {
        "ticker": "VYX",
        "company": "NCR Voyix",
        "change_pct": -36.82,
        "price": 6.49
      },
      {
        "ticker": "LSPD",
        "company": "Lightspeed",
        "change_pct": -28.32,
        "price": 8.68
      },
      {
        "ticker": "FOUR",
        "company": "Shift4",
        "change_pct": -36.78,
        "price": 41.47
      },
      {
        "ticker": "XYZ",
        "company": "Block (Square)",
        "change_pct": -2.58,
        "price": 69.62
      },
      {
        "ticker": "GPN",
        "company": "Global Payments",
        "change_pct": -11.51,
        "price": 68.36
      },
      {
        "ticker": "FISV",
        "company": "Fiserv",
        "change_pct": -18.48,
        "price": 56.01
      },
      {
        "ticker": "UBER",
        "company": "Uber",
        "change_pct": -13.7,
        "price": 74.38
      }
    ]
  }
}